class test
{
	field static int i
	field static int j
	field static int v1 = 5
	field static int v2 = 8
	field static int tmp = 0
	method public static void main(java.lang.String[])
	max_stack 15
	max_locals 15
	{
			sipush 1
			istore 0
			Lbegin0: 
			nop
			iload 0
			getstatic int test.v1
			isub
			ifgt L1
			iconst_0
			goto L2
			L1: 
			nop
			iconst_1
			L2: 
			nop
			ifne Lexit0
				getstatic int test.v2
				istore 1
				Lbegin3: 
				nop
				iload 1
				sipush 3
				isub
				iflt L4
				iconst_0
				goto L5
				L4: 
				nop
				iconst_1
				L5: 
				nop
				ifne Lexit3
				getstatic int test.tmp
				sipush 1
				iadd
				putstatic int test.tmp
				iload 1
				sipush 1
				isub
				istore 1
				goto Lbegin3
				Lexit3: 
				nop
			getstatic java.io.PrintStream java.lang.System.out
			getstatic int test.tmp
			invokevirtual void java.io.PrintStream.print(int)
			getstatic java.io.PrintStream java.lang.System.out
			invokevirtual void java.io.PrintStream.println()
			iload 0
			sipush 1
			iadd
			istore 0
			goto Lbegin0
			Lexit0: 
			nop
		getstatic java.io.PrintStream java.lang.System.out
		invokevirtual void java.io.PrintStream.println()
			getstatic int test.v1
			istore 0
			Lbegin6: 
			nop
			iload 0
			sipush 1
			isub
			iflt L7
			iconst_0
			goto L8
			L7: 
			nop
			iconst_1
			L8: 
			nop
			ifne Lexit6
				sipush 3
				istore 1
				Lbegin9: 
				nop
				iload 1
				getstatic int test.v2
				isub
				ifgt L10
				iconst_0
				goto L11
				L10: 
				nop
				iconst_1
				L11: 
				nop
				ifne Lexit9
				iload 1
				sipush 1
				iadd
				istore 1
				goto Lbegin9
				Lexit9: 
				nop
			iload 0
			sipush 1
			isub
			istore 0
			goto Lbegin6
			Lexit6: 
			nop
		getstatic java.io.PrintStream java.lang.System.out
		invokevirtual void java.io.PrintStream.println()
		return
	}
}